sql_inspect/__init__.py
sql_inspect/_core.py
sql_inspect/middleware.py
sql_inspect-2.0.1.dist-info/licenses/LICENSE
sql_inspect-2.0.1.dist-info/METADATA
sql_inspect-2.0.1.dist-info/WHEEL
sql_inspect-2.0.1.dist-info/top_level.txt
sql_inspect-2.0.1.dist-info/RECORD
