Metadata-Version: 2.4
Name: sql-inspect
Version: 2.0.1
Summary: Enhanced Django middleware for monitoring, analyzing, and optimizing database SQL queries
Author-email: Paul Onyekwelu <paulonyekweluo@gmail.com>
License: MIT
Project-URL: Homepage, https://sql-inspect.readthedocs.io/en/latest/
Project-URL: Repository, https://github.com/AgenticAiLabs/sql-inspect
Project-URL: Issues, https://github.com/AgenticAiLabs/sql-inspect/issues
Keywords: django,sql,monitoring,logging,performance,debugging,middleware,async,optimization
Requires-Python: >=3.8
License-File: LICENSE
Requires-Dist: Django>=3.2
Requires-Dist: sqlparse>=0.4.4
Requires-Dist: Pygments>=2.17.2
Requires-Dist: cachetools
Dynamic: license-file
